aiosmtplib/__init__.py
aiosmtplib/__main__.py
aiosmtplib/api.py
aiosmtplib/auth.py
aiosmtplib/compat.py
aiosmtplib/connection.py
aiosmtplib/default.py
aiosmtplib/email.py
aiosmtplib/errors.py
aiosmtplib/esmtp.py
aiosmtplib/protocol.py
aiosmtplib/py.typed
aiosmtplib/response.py
aiosmtplib/smtp.py
aiosmtplib/status.py
aiosmtplib/sync.py
aiosmtplib-1.1.5.dist-info/LICENSE.txt
aiosmtplib-1.1.5.dist-info/WHEEL
aiosmtplib-1.1.5.dist-info/METADATA
aiosmtplib-1.1.5.dist-info/RECORD
