Metadata-Version: 2.1
Name: aiosmtplib
Version: 1.1.5
Summary: asyncio SMTP client
Home-page: https://github.com/cole/aiosmtplib
License: MIT
Keywords: smtp,email,asyncio
Author: Cole Maclean
Author-email: hi@colemaclean.dev
Requires-Python: >=3.5.2,<4.0.0
Classifier: Development Status :: 5 - Production/Stable
Classifier: Environment :: No Input/Output (Daemon)
Classifier: Framework :: AsyncIO
Classifier: Intended Audience :: Developers
Classifier: License :: OSI Approved :: MIT License
Classifier: Natural Language :: English
Classifier: Operating System :: OS Independent
Classifier: Programming Language :: Python :: 3
Classifier: Programming Language :: Python :: 3.6
Classifier: Programming Language :: Python :: 3.7
Classifier: Programming Language :: Python :: 3.8
Classifier: Programming Language :: Python :: 3.9
Classifier: Topic :: Communications
Classifier: Topic :: Communications :: Email
Classifier: Topic :: Software Development :: Libraries
Classifier: Topic :: Software Development :: Libraries :: Python Modules
Classifier: Typing :: Typed
Provides-Extra: docs
Provides-Extra: uvloop
Requires-Dist: sphinx (>=2,<4); extra == "docs"
Requires-Dist: sphinx_autodoc_typehints (>=1.7.0,<2.0.0); extra == "docs"
Requires-Dist: uvloop (>=0.13,<0.15); extra == "uvloop"
Project-URL: Documentation, https://aiosmtplib.readthedocs.io/en/stable/
Project-URL: Repository, https://github.com/cole/aiosmtplib
